cputemp/__init__.py
cputemp/cputemp.py
cputemp-0.0.7.dist-info/LICENSE
cputemp-0.0.7.dist-info/METADATA
cputemp-0.0.7.dist-info/WHEEL
cputemp-0.0.7.dist-info/entry_points.txt
cputemp-0.0.7.dist-info/top_level.txt
cputemp-0.0.7.dist-info/RECORD
