Metadata-Version: 2.1
Name: cputemp
Version: 0.0.7
Summary: Show Raspberry Pi's or Orange Pi's CPU temperature
Home-page: https://github.com/gyengus/cputemp
Author: Gyengus
Author-email: gyengus@gmail.com
License: UNKNOWN
Platform: UNKNOWN
Classifier: Programming Language :: Python :: 3
Classifier: License :: OSI Approved :: Mozilla Public License 2.0 (MPL 2.0)
Classifier: Operating System :: POSIX :: Linux
